MANIFEST.in
setup.py
containmentUnit/__init__.py
containmentUnit/websetup.py
containmentUnit.egg-info/PKG-INFO
containmentUnit.egg-info/SOURCES.txt
containmentUnit.egg-info/dependency_links.txt
containmentUnit.egg-info/entry_points.txt
containmentUnit.egg-info/not-zip-safe
containmentUnit.egg-info/paster_plugins.txt
containmentUnit.egg-info/top_level.txt
containmentUnit/config/__init__.py
containmentUnit/config/deployment.ini_tmpl
containmentUnit/config/environment.py
containmentUnit/config/middleware.py
containmentUnit/config/routing.py
containmentUnit/config/thirdPartyPaths.json
containmentUnit/controllers/__init__.py
containmentUnit/controllers/casperjs.py
containmentUnit/controllers/chart.py
containmentUnit/controllers/combine.py
containmentUnit/controllers/error.py
containmentUnit/controllers/migration.py
containmentUnit/controllers/results.py
containmentUnit/controllers/superposed.py
containmentUnit/controllers/wraith.py
containmentUnit/dependencyMods/readme.txt
containmentUnit/dependencyMods/bmpExtract/__init__.py
containmentUnit/dependencyMods/bmpExtract/__init__.pyc
containmentUnit/dependencyMods/bmpExtract/client.py
containmentUnit/dependencyMods/bmpExtract/client.pyc
containmentUnit/dependencyMods/bmpExtract/server.py
containmentUnit/dependencyMods/bmpExtract/server.pyc
containmentUnit/dependencyMods/bmpExtract/webdriver_event_listener.py
containmentUnit/dependencyMods/bmpExtract/webdriver_event_listener.pyc
containmentUnit/dependencyMods/executableBase/harStorage.bat
containmentUnit/dependencyMods/executableBase/harStorage.log
containmentUnit/dependencyMods/executableBase/harStorageV1.bat
containmentUnit/dependencyMods/executableBase/harStorageV2.bat
containmentUnit/dependencyMods/executableBase/production.ini
containmentUnit/dependencyMods/wraith_customFiles/gallery.rb
containmentUnit/dependencyMods/wraith_customFiles/slideshow_template.erb
containmentUnit/lib/HAR.py
containmentUnit/lib/Math.py
containmentUnit/lib/MongoHandler.py
containmentUnit/lib/__init__.py
containmentUnit/lib/app_globals.py
containmentUnit/lib/base.py
containmentUnit/lib/helpers.py
containmentUnit/lib/proxyPortManager.py
containmentUnit/public/favicon.ico
containmentUnit/public/Wraith/configs/existingSites.config
