Metadata-Version: 1.1
Name: containmentUnit
Version: 1.0.13
Summary: A collection of front end performance measurement tools.
Home-page: https://github.com/DecipherOne/containmentUnit
Author: Will Canada
Author-email: willc@decipherone.com
License: BSD, see LICENSE.txt for details
Platform: Linux
Platform: Windows
Classifier: Development Status :: 4 - Beta
Classifier: Intended Audience :: Developers
Classifier: Intended Audience :: Information Technology
Classifier: Topic :: Software Development :: Testing
Classifier: License :: OSI Approved :: BSD License
Classifier: Programming Language :: Python :: 2.7
